{
  "LV": 0,
  "StartInOrbit": true,
  "ScheduledLaunchTime": "1968-12-21T14:24:00",
  "InitialTimeToRetrograde": "6.06:00:00",
  "MissionCommands": [
    {
      "Delivered": false,
      "Processed": false,
      "Completed": false,
      "Priority": false,
      "ID": "c360e045-ed72-4e45-93f5-ec21de62ab29",
      "Action": 0,
      "Timestamp": 25.0,
      "DisplayTime": 6.0,
      "From": 0,
      "Message": "예정된 지구 귀환 궤도 진입(TEI) 연소까지 약 30분 남았습니다. 우주선을 설정하고 연소를 준비합시다.",
      "Value1": 0.0,
      "Value2": 0.0,
      "Value3": 0.0,
      "String1": "",
      "String2": "",
      "String3": "",
      "Bool1": false,
      "ThresholdLimit": 0.0,
      "PinID": 0,
      "PinPosition": 0,
      "KnobID": 0,
      "ButtonId": 0,
      "FuseID": 0,
      "FusePosition": 0,
      "LM_PinID": 0,
      "LM_PinPosition": 0,
      "LM_KnobID": 0,
      "LM_ButtonId": 0,
      "LM_FuseID": 0,
      "LM_FusePosition": 0,
      "Fault": 0,
      "Failure": 0,
      "PlayAudioClip_String3": false
    },
    {
      "Delivered": false,
      "Processed": false,
      "Completed": false,
      "Priority": false,
      "ID": "4fb6f873-456c-4a40-96fb-948be3a49778",
      "Action": 759,
      "Timestamp": 25.0,
      "DisplayTime": 6.0,
      "From": 1,
      "Message": "확인, C-메뉴를 사용해 TEI 플래너를 열고, 달로부터 탈출 속도에 오르며 근지점(Pe) 3464 nmi(고도 20-23 nmi)를 목표로 하는 연소를 설정하세요. 탈출 속도 비율 1.099246으로 시작하면 됩니다.",
      "Value1": 0.0,
      "Value2": 0.0,
      "Value3": 0.0,
      "String1": "",
      "String2": "",
      "String3": "",
      "Bool1": false,
      "ThresholdLimit": 0.0,
      "PinID": 0,
      "PinPosition": 0,
      "KnobID": 0,
      "ButtonId": 0,
      "FuseID": 0,
      "FusePosition": 0,
      "LM_PinID": 0,
      "LM_PinPosition": 0,
      "LM_KnobID": 0,
      "LM_ButtonId": 0,
      "LM_FuseID": 0,
      "LM_FusePosition": 0,
      "Fault": 0,
      "Failure": 0,
      "PlayAudioClip_String3": false
    },
    {
      "Delivered": false,
      "Processed": false,
      "Completed": false,
      "Priority": false,
      "ID": "79edaaf9-57c9-4d57-b536-3bfd69b8caa8",
      "Action": 760,
      "Timestamp": 25.0,
      "DisplayTime": 6.0,
      "From": 1,
      "Message": "Pe 3464 nmi이면 진입각 6.5도의 궤적에 오르게 될 것입니다. 궤적이 만족스러우면 REQUEST를 누르세요.",
      "Value1": 0.0,
      "Value2": 0.0,
      "Value3": 0.0,
      "String1": "",
      "String2": "",
      "String3": "",
      "Bool1": false,
      "ThresholdLimit": 0.0,
      "PinID": 0,
      "PinPosition": 0,
      "KnobID": 0,
      "ButtonId": 0,
      "FuseID": 0,
      "FusePosition": 0,
      "LM_PinID": 0,
      "LM_PinPosition": 0,
      "LM_KnobID": 0,
      "LM_ButtonId": 0,
      "LM_FuseID": 0,
      "LM_FusePosition": 0,
      "Fault": 0,
      "Failure": 0,
      "PlayAudioClip_String3": false
    },
    {
      "Delivered": false,
      "Processed": false,
      "Completed": false,
      "Priority": false,
      "ID": "b455c7de-dfd1-4a6c-a059-833622286610",
      "Action": 204,
      "Timestamp": 25.0,
      "DisplayTime": 6.0,
      "From": 0,
      "Message": "연소가 요청되었습니다. 다음으로 P30을 실행하겠습니다.",
      "Value1": 30.0,
      "Value2": 0.0,
      "Value3": 0.0,
      "String1": "",
      "String2": "",
      "String3": "",
      "Bool1": false,
      "ThresholdLimit": 0.0,
      "PinID": 0,
      "PinPosition": 0,
      "KnobID": 0,
      "ButtonId": 0,
      "FuseID": 0,
      "FusePosition": 0,
      "LM_PinID": 0,
      "LM_PinPosition": 0,
      "LM_KnobID": 0,
      "LM_ButtonId": 0,
      "LM_FuseID": 0,
      "LM_FusePosition": 0,
      "Fault": 0,
      "Failure": 0,
      "PlayAudioClip_String3": false
    },
    {
      "Delivered": false,
      "Processed": false,
      "Completed": false,
      "Priority": false,
      "ID": "60e706cd-42b5-4fcb-b69a-95e8ce1d8ce1",
      "Action": 0,
      "Timestamp": 25.0,
      "DisplayTime": 6.0,
      "From": 0,
      "Message": "P30. 연소를 설정하는 중입니다.",
      "Value1": 0.0,
      "Value2": 0.0,
      "Value3": 0.0,
      "String1": "",
      "String2": "",
      "String3": "",
      "Bool1": false,
      "ThresholdLimit": 0.0,
      "PinID": 0,
      "PinPosition": 0,
      "KnobID": 0,
      "ButtonId": 0,
      "FuseID": 0,
      "FusePosition": 0,
      "LM_PinID": 0,
      "LM_PinPosition": 0,
      "LM_KnobID": 0,
      "LM_ButtonId": 0,
      "LM_FuseID": 0,
      "LM_FusePosition": 0,
      "Fault": 0,
      "Failure": 0,
      "PlayAudioClip_String3": false
    },
    {
      "Delivered": false,
      "Processed": false,
      "Completed": false,
      "Priority": false,
      "ID": "762ef7ac-0379-44e6-8f99-ed498411e1e7",
      "Action": 1,
      "Timestamp": 25.0,
      "DisplayTime": 6.0,
      "From": 1,
      "Message": "확인, P30이 N42를 표시하면 R2에는 현재 Pe, 즉 약 고도 60 nmi가 표시되어야 하고, R1에는 목표 Ap가 표시되는데 이는 우리의 탈출 궤적을 나타내는 포물선 궤도이므로 음수여야 합니다. 준비되면 알려주세요.",
      "Value1": 0.0,
      "Value2": 0.0,
      "Value3": 0.0,
      "String1": "READY",
      "String2": "",
      "String3": "",
      "Bool1": false,
      "ThresholdLimit": 0.0,
      "PinID": 0,
      "PinPosition": 0,
      "KnobID": 0,
      "ButtonId": 0,
      "FuseID": 0,
      "FusePosition": 0,
      "LM_PinID": 0,
      "LM_PinPosition": 0,
      "LM_KnobID": 0,
      "LM_ButtonId": 0,
      "LM_FuseID": 0,
      "LM_FusePosition": 0,
      "Fault": 0,
      "Failure": 0,
      "PlayAudioClip_String3": false
    },
    {
      "Delivered": false,
      "Processed": false,
      "Completed": false,
      "Priority": false,
      "ID": "d9c5cf07-ac18-4123-b4d5-35245aa5e2f9",
      "Action": 204,
      "Timestamp": 25.0,
      "DisplayTime": 6.0,
      "From": 1,
      "Message": "좋습니다, P52를 사용해 연소에 적합한 플랫폼으로 IMU를 정렬하세요. V37E 52E를 입력해 P52를 실행하세요.",
      "Value1": 52.0,
      "Value2": 0.0,
      "Value3": 0.0,
      "String1": "",
      "String2": "",
      "String3": "",
      "Bool1": false,
      "ThresholdLimit": 0.0,
      "PinID": 0,
      "PinPosition": 0,
      "KnobID": 0,
      "ButtonId": 0,
      "FuseID": 0,
      "FusePosition": 0,
      "LM_PinID": 0,
      "LM_PinPosition": 0,
      "LM_KnobID": 0,
      "LM_ButtonId": 0,
      "LM_FuseID": 0,
      "LM_FusePosition": 0,
      "Fault": 0,
      "Failure": 0,
      "PlayAudioClip_String3": false
    },
    {
      "Delivered": false,
      "Processed": false,
      "Completed": false,
      "Priority": false,
      "ID": "861c0b36-f301-4834-adc3-a6467e90e29c",
      "Action": 1,
      "Timestamp": 25.0,
      "DisplayTime": 6.0,
      "From": 1,
      "Message": "옵션 1로 진행하고, 체크리스트를 따라도 좋습니다. IMU 정렬이 끝나면 READY를 누르세요.",
      "Value1": 0.0,
      "Value2": 0.0,
      "Value3": 0.0,
      "String1": "READY",
      "String2": "",
      "String3": "",
      "Bool1": false,
      "ThresholdLimit": 0.0,
      "PinID": 0,
      "PinPosition": 0,
      "KnobID": 0,
      "ButtonId": 0,
      "FuseID": 0,
      "FusePosition": 0,
      "LM_PinID": 0,
      "LM_PinPosition": 0,
      "LM_KnobID": 0,
      "LM_ButtonId": 0,
      "LM_FuseID": 0,
      "LM_FusePosition": 0,
      "Fault": 0,
      "Failure": 0,
      "PlayAudioClip_String3": false
    },
    {
      "Delivered": false,
      "Processed": false,
      "Completed": false,
      "Priority": false,
      "ID": "e1d3ee4a-de37-4ccb-ad74-4b72697cc3c7",
      "Action": 1,
      "Timestamp": 25.0,
      "DisplayTime": 6.0,
      "From": 1,
      "Message": "진행하기 전에 V49E를 입력하고 자동 기동 루틴(체크리스트: G&C GENERAL -> (V49) CREW DEF MNVR)을 완료하세요. 완료되면 DONE을 누르세요.",
      "Value1": 0.0,
      "Value2": 0.0,
      "Value3": 0.0,
      "String1": "DONE",
      "String2": "",
      "String3": "",
      "Bool1": false,
      "ThresholdLimit": 0.0,
      "PinID": 0,
      "PinPosition": 0,
      "KnobID": 0,
      "ButtonId": 0,
      "FuseID": 0,
      "FusePosition": 0,
      "LM_PinID": 0,
      "LM_PinPosition": 0,
      "LM_KnobID": 0,
      "LM_ButtonId": 0,
      "LM_FuseID": 0,
      "LM_FusePosition": 0,
      "Fault": 0,
      "Failure": 0,
      "PlayAudioClip_String3": false
    },
    {
      "Delivered": false,
      "Processed": false,
      "Completed": false,
      "Priority": false,
      "ID": "4e11d5ca-a105-48b9-87b9-fc3e70742216",
      "Action": 204,
      "Timestamp": 25.0,
      "DisplayTime": 6.0,
      "From": 1,
      "Message": "(P40) G&N SPS THRUSTING 체크리스트를 사용해 P40을 실행하고 SPS와 우주선을 연소 준비 상태로 만드세요.",
      "Value1": 40.0,
      "Value2": 0.0,
      "Value3": 0.0,
      "String1": "",
      "String2": "",
      "String3": "",
      "Bool1": false,
      "ThresholdLimit": 0.0,
      "PinID": 0,
      "PinPosition": 0,
      "KnobID": 0,
      "ButtonId": 0,
      "FuseID": 0,
      "FusePosition": 0,
      "LM_PinID": 0,
      "LM_PinPosition": 0,
      "LM_KnobID": 0,
      "LM_ButtonId": 0,
      "LM_FuseID": 0,
      "LM_FusePosition": 0,
      "Fault": 0,
      "Failure": 0,
      "PlayAudioClip_String3": false
    },
    {
      "Delivered": false,
      "Processed": false,
      "Completed": false,
      "Priority": false,
      "ID": "2ba943c2-d046-426b-afa5-6bed0be9e050",
      "Action": 0,
      "Timestamp": 25.0,
      "DisplayTime": 6.0,
      "From": 0,
      "Message": "P40. ",
      "Value1": 0.0,
      "Value2": 0.0,
      "Value3": 0.0,
      "String1": "",
      "String2": "",
      "String3": "",
      "Bool1": false,
      "ThresholdLimit": 0.0,
      "PinID": 0,
      "PinPosition": 0,
      "KnobID": 0,
      "ButtonId": 0,
      "FuseID": 0,
      "FusePosition": 0,
      "LM_PinID": 0,
      "LM_PinPosition": 0,
      "LM_KnobID": 0,
      "LM_ButtonId": 0,
      "LM_FuseID": 0,
      "LM_FusePosition": 0,
      "Fault": 0,
      "Failure": 0,
      "PlayAudioClip_String3": false
    },
    {
      "Delivered": false,
      "Processed": false,
      "Completed": false,
      "Priority": false,
      "ID": "a2a00b41-fce6-40bc-bdb4-a4c9c31a6b3e",
      "Action": 18,
      "Timestamp": 25.0,
      "DisplayTime": 6.0,
      "From": 3,
      "Message": "체크리스트를 따르고 필요한 만큼 타임스케일을 사용해 T -2분까지 진행하세요.",
      "Value1": 120.0,
      "Value2": 0.0,
      "Value3": 0.0,
      "String1": "",
      "String2": "",
      "String3": "",
      "Bool1": false,
      "ThresholdLimit": 0.0,
      "PinID": 0,
      "PinPosition": 0,
      "KnobID": 0,
      "ButtonId": 0,
      "FuseID": 0,
      "FusePosition": 0,
      "LM_PinID": 0,
      "LM_PinPosition": 0,
      "LM_KnobID": 0,
      "LM_ButtonId": 0,
      "LM_FuseID": 0,
      "LM_FusePosition": 0,
      "Fault": 0,
      "Failure": 0,
      "PlayAudioClip_String3": false
    },
    {
      "Delivered": false,
      "Processed": false,
      "Completed": false,
      "Priority": false,
      "ID": "5ed7d65c-3cf2-41c3-a98e-cff52a1e98aa",
      "Action": 1,
      "Timestamp": 25.0,
      "DisplayTime": 6.0,
      "From": 0,
      "Message": "T -2분.",
      "Value1": 0.0,
      "Value2": 0.0,
      "Value3": 0.0,
      "String1": "",
      "String2": "",
      "String3": "",
      "Bool1": false,
      "ThresholdLimit": 0.0,
      "PinID": 131,
      "PinPosition": 4,
      "KnobID": 0,
      "ButtonId": 0,
      "FuseID": 0,
      "FusePosition": 0,
      "LM_PinID": 0,
      "LM_PinPosition": 0,
      "LM_KnobID": 0,
      "LM_ButtonId": 0,
      "LM_FuseID": 0,
      "LM_FusePosition": 0,
      "Fault": 0,
      "Failure": 0,
      "PlayAudioClip_String3": false
    },
    {
      "Delivered": false,
      "Processed": false,
      "Completed": false,
      "Priority": false,
      "ID": "0f77fea0-b3e3-4af2-9c96-7c421b158f78",
      "Action": 18,
      "Timestamp": 25.0,
      "DisplayTime": 6.0,
      "From": 0,
      "Message": "SPS가 활성화되었습니다. 점화를 준비하세요.",
      "Value1": 60.0,
      "Value2": 0.0,
      "Value3": 0.0,
      "String1": "",
      "String2": "",
      "String3": "",
      "Bool1": false,
      "ThresholdLimit": 0.0,
      "PinID": 0,
      "PinPosition": 0,
      "KnobID": 0,
      "ButtonId": 0,
      "FuseID": 0,
      "FusePosition": 0,
      "LM_PinID": 0,
      "LM_PinPosition": 0,
      "LM_KnobID": 0,
      "LM_ButtonId": 0,
      "LM_FuseID": 0,
      "LM_FusePosition": 0,
      "Fault": 0,
      "Failure": 0,
      "PlayAudioClip_String3": false
    },
    {
      "Delivered": false,
      "Processed": false,
      "Completed": false,
      "Priority": false,
      "ID": "f66846c3-a7a7-4d15-a460-f3128b10b030",
      "Action": 0,
      "Timestamp": 25.0,
      "DisplayTime": 6.0,
      "From": 3,
      "Message": "T-60초. 자세를 확인하고, 필요하면 DIRECT를 사용해 조정하세요.",
      "Value1": 0.0,
      "Value2": 0.0,
      "Value3": 0.0,
      "String1": "",
      "String2": "",
      "String3": "",
      "Bool1": false,
      "ThresholdLimit": 0.0,
      "PinID": 0,
      "PinPosition": 0,
      "KnobID": 0,
      "ButtonId": 0,
      "FuseID": 0,
      "FusePosition": 0,
      "LM_PinID": 0,
      "LM_PinPosition": 0,
      "LM_KnobID": 0,
      "LM_ButtonId": 0,
      "LM_FuseID": 0,
      "LM_FusePosition": 0,
      "Fault": 0,
      "Failure": 0,
      "PlayAudioClip_String3": false
    },
    {
      "Delivered": false,
      "Processed": false,
      "Completed": false,
      "Priority": false,
      "ID": "c7dad59c-9d99-4e17-b6c2-d351f96a4cab",
      "Action": 164,
      "Timestamp": 25.0,
      "DisplayTime": 6.0,
      "From": 0,
      "Message": "확인, 이번에는 점화가 잘 되길 바랍시다!",
      "Value1": 0.0,
      "Value2": 0.0,
      "Value3": 0.0,
      "String1": "",
      "String2": "",
      "String3": "",
      "Bool1": false,
      "ThresholdLimit": 0.0,
      "PinID": 0,
      "PinPosition": 0,
      "KnobID": 0,
      "ButtonId": 0,
      "FuseID": 0,
      "FusePosition": 0,
      "LM_PinID": 0,
      "LM_PinPosition": 0,
      "LM_KnobID": 0,
      "LM_ButtonId": 0,
      "LM_FuseID": 0,
      "LM_FusePosition": 0,
      "Fault": 0,
      "Failure": 0,
      "PlayAudioClip_String3": false
    },
    {
      "Delivered": false,
      "Processed": false,
      "Completed": false,
      "Priority": false,
      "ID": "2b927a12-cb98-4e7a-96a2-edcbaf8413e6",
      "Action": 0,
      "Timestamp": 25.0,
      "DisplayTime": 6.0,
      "From": 0,
      "Message": "점화!",
      "Value1": 0.0,
      "Value2": 0.0,
      "Value3": 0.0,
      "String1": "",
      "String2": "",
      "String3": "",
      "Bool1": false,
      "ThresholdLimit": 0.0,
      "PinID": 0,
      "PinPosition": 0,
      "KnobID": 0,
      "ButtonId": 0,
      "FuseID": 0,
      "FusePosition": 0,
      "LM_PinID": 0,
      "LM_PinPosition": 0,
      "LM_KnobID": 0,
      "LM_ButtonId": 0,
      "LM_FuseID": 0,
      "LM_FusePosition": 0,
      "Fault": 0,
      "Failure": 0,
      "PlayAudioClip_String3": false
    },
    {
      "Delivered": false,
      "Processed": false,
      "Completed": false,
      "Priority": false,
      "ID": "63bb8202-1e50-437c-97a1-5982166b56e8",
      "Action": 0,
      "Timestamp": 25.0,
      "DisplayTime": 6.0,
      "From": 3,
      "Message": "아주 좋습니다. CSM이 더 가벼워졌으니, 며칠 전에 했던 달 궤도 진입 연소보다 이번 연소는 더 짧을 것입니다.",
      "Value1": 0.0,
      "Value2": 0.0,
      "Value3": 0.0,
      "String1": "",
      "String2": "",
      "String3": "",
      "Bool1": false,
      "ThresholdLimit": 0.0,
      "PinID": 0,
      "PinPosition": 0,
      "KnobID": 0,
      "ButtonId": 0,
      "FuseID": 0,
      "FusePosition": 0,
      "LM_PinID": 0,
      "LM_PinPosition": 0,
      "LM_KnobID": 0,
      "LM_ButtonId": 0,
      "LM_FuseID": 0,
      "LM_FusePosition": 0,
      "Fault": 0,
      "Failure": 0,
      "PlayAudioClip_String3": false
    },
    {
      "Delivered": false,
      "Processed": false,
      "Completed": false,
      "Priority": false,
      "ID": "b691b2a4-c311-43f6-8f5a-f87e9862747c",
      "Action": 165,
      "Timestamp": 25.0,
      "DisplayTime": 6.0,
      "From": 0,
      "Message": "네, 연소 시간은 2분 43초로 추정됩니다.",
      "Value1": 0.0,
      "Value2": 0.0,
      "Value3": 0.0,
      "String1": "",
      "String2": "",
      "String3": "",
      "Bool1": false,
      "ThresholdLimit": 0.0,
      "PinID": 0,
      "PinPosition": 0,
      "KnobID": 0,
      "ButtonId": 0,
      "FuseID": 0,
      "FusePosition": 0,
      "LM_PinID": 0,
      "LM_PinPosition": 0,
      "LM_KnobID": 0,
      "LM_ButtonId": 0,
      "LM_FuseID": 0,
      "LM_FusePosition": 0,
      "Fault": 0,
      "Failure": 0,
      "PlayAudioClip_String3": false
    },
    {
      "Delivered": false,
      "Processed": false,
      "Completed": false,
      "Priority": false,
      "ID": "74f636bf-ca21-4fa4-9e17-ed19b68ecf9c",
      "Action": 0,
      "Timestamp": 25.0,
      "DisplayTime": 6.0,
      "From": 0,
      "Message": "연소 완료, 이제 달로부터의 탈출 궤적에 올랐을 것입니다.",
      "Value1": 0.0,
      "Value2": 0.0,
      "Value3": 0.0,
      "String1": "",
      "String2": "",
      "String3": "",
      "Bool1": false,
      "ThresholdLimit": 0.0,
      "PinID": 0,
      "PinPosition": 0,
      "KnobID": 0,
      "ButtonId": 0,
      "FuseID": 0,
      "FusePosition": 0,
      "LM_PinID": 0,
      "LM_PinPosition": 0,
      "LM_KnobID": 0,
      "LM_ButtonId": 0,
      "LM_FuseID": 0,
      "LM_FusePosition": 0,
      "Fault": 0,
      "Failure": 0,
      "PlayAudioClip_String3": false
    },
    {
      "Delivered": false,
      "Processed": false,
      "Completed": false,
      "Priority": false,
      "ID": "6e75cdd0-318a-46e5-a121-2ae07027a79d",
      "Action": 0,
      "Timestamp": 25.0,
      "DisplayTime": 6.0,
      "From": 3,
      "Message": "그러네요. 기분이 이상하지 않나요?",
      "Value1": 0.0,
      "Value2": 0.0,
      "Value3": 0.0,
      "String1": "",
      "String2": "",
      "String3": "",
      "Bool1": false,
      "ThresholdLimit": 0.0,
      "PinID": 0,
      "PinPosition": 0,
      "KnobID": 0,
      "ButtonId": 0,
      "FuseID": 0,
      "FusePosition": 0,
      "LM_PinID": 0,
      "LM_PinPosition": 0,
      "LM_KnobID": 0,
      "LM_ButtonId": 0,
      "LM_FuseID": 0,
      "LM_FusePosition": 0,
      "Fault": 0,
      "Failure": 0,
      "PlayAudioClip_String3": false
    },
    {
      "Delivered": false,
      "Processed": false,
      "Completed": false,
      "Priority": false,
      "ID": "5a875b21-1487-4c3b-8e03-786031b338a4",
      "Action": 0,
      "Timestamp": 25.0,
      "DisplayTime": 6.0,
      "From": 1,
      "Message": "확실히 그렇습니다. 달에 도달하고 궤도를 도는 며칠이 정말 흥미진진했습니다.",
      "Value1": 0.0,
      "Value2": 0.0,
      "Value3": 0.0,
      "String1": "",
      "String2": "",
      "String3": "",
      "Bool1": false,
      "ThresholdLimit": 0.0,
      "PinID": 0,
      "PinPosition": 0,
      "KnobID": 0,
      "ButtonId": 0,
      "FuseID": 0,
      "FusePosition": 0,
      "LM_PinID": 0,
      "LM_PinPosition": 0,
      "LM_KnobID": 0,
      "LM_ButtonId": 0,
      "LM_FuseID": 0,
      "LM_FusePosition": 0,
      "Fault": 0,
      "Failure": 0,
      "PlayAudioClip_String3": false
    },
    {
      "Delivered": false,
      "Processed": false,
      "Completed": false,
      "Priority": false,
      "ID": "cd40f10f-0b41-4232-8a79-dd5e488e088e",
      "Action": 0,
      "Timestamp": 25.0,
      "DisplayTime": 6.0,
      "From": 3,
      "Message": "정말 그렇습니다, 그리고 지구와 다시 신호를 획득하면 이 고도에서 지구돋이(Earthrise)와 달 표면의 멋진 마지막 모습을 볼 수 있을 것입니다.",
      "Value1": 0.0,
      "Value2": 0.0,
      "Value3": 0.0,
      "String1": "",
      "String2": "",
      "String3": "",
      "Bool1": false,
      "ThresholdLimit": 0.0,
      "PinID": 0,
      "PinPosition": 0,
      "KnobID": 0,
      "ButtonId": 0,
      "FuseID": 0,
      "FusePosition": 0,
      "LM_PinID": 0,
      "LM_PinPosition": 0,
      "LM_KnobID": 0,
      "LM_ButtonId": 0,
      "LM_FuseID": 0,
      "LM_FusePosition": 0,
      "Fault": 0,
      "Failure": 0,
      "PlayAudioClip_String3": false
    },
    {
      "Delivered": false,
      "Processed": false,
      "Completed": false,
      "Priority": false,
      "ID": "67746eef-2248-4dc4-8bb1-c4451d7342ee",
      "Action": 0,
      "Timestamp": 25.0,
      "DisplayTime": 6.0,
      "From": 0,
      "Message": "당신의 의도는 잘 모르겠지만, 저는 확실히 저 LEM을 몰고 달 표면에 착륙할 계획입니다.",
      "Value1": 0.0,
      "Value2": 0.0,
      "Value3": 0.0,
      "String1": "",
      "String2": "",
      "String3": "",
      "Bool1": false,
      "ThresholdLimit": 0.0,
      "PinID": 0,
      "PinPosition": 0,
      "KnobID": 0,
      "ButtonId": 0,
      "FuseID": 0,
      "FusePosition": 0,
      "LM_PinID": 0,
      "LM_PinPosition": 0,
      "LM_KnobID": 0,
      "LM_ButtonId": 0,
      "LM_FuseID": 0,
      "LM_FusePosition": 0,
      "Fault": 0,
      "Failure": 0,
      "PlayAudioClip_String3": false
    },
    {
      "Delivered": false,
      "Processed": false,
      "Completed": false,
      "Priority": false,
      "ID": "68ef7fa9-81f5-454e-8247-de24833a7c3f",
      "Action": 52,
      "Timestamp": 25.0,
      "DisplayTime": 6.0,
      "From": 1,
      "Message": "오, 그렇군요. 지금은 체크리스트를 완료하고 지구돋이를 보기 좋은 자세로 기동합시다. 프로그레이드 방향으로 달 지평선을 따라 떠오를 것입니다. 지평선은 별이 없는 커다란 검은 영역으로 보일 것입니다. ORDEAL을 ORB RATE로 설정하면 더 쉽게 찾을 수 있습니다(ORDEAL ORB RATE에서 피치를 300으로 설정).",
      "Value1": 0.0,
      "Value2": 0.0,
      "Value3": 0.0,
      "String1": "",
      "String2": "",
      "String3": "",
      "Bool1": false,
      "ThresholdLimit": 0.0,
      "PinID": 0,
      "PinPosition": 0,
      "KnobID": 0,
      "ButtonId": 0,
      "FuseID": 0,
      "FusePosition": 0,
      "LM_PinID": 0,
      "LM_PinPosition": 0,
      "LM_KnobID": 0,
      "LM_ButtonId": 0,
      "LM_FuseID": 0,
      "LM_FusePosition": 0,
      "Fault": 0,
      "Failure": 0,
      "PlayAudioClip_String3": false
    },
    {
      "Delivered": false,
      "Processed": false,
      "Completed": false,
      "Priority": false,
      "ID": "1ae225eb-cbb1-4dbc-baec-05784a79c3d7",
      "Action": 0,
      "Timestamp": 25.0,
      "DisplayTime": 6.0,
      "From": 2,
      "Message": "{{capsuleName}}, 들립니까?",
      "Value1": 0.0,
      "Value2": 0.0,
      "Value3": 0.0,
      "String1": "",
      "String2": "",
      "String3": "",
      "Bool1": false,
      "ThresholdLimit": 0.0,
      "PinID": 0,
      "PinPosition": 0,
      "KnobID": 0,
      "ButtonId": 0,
      "FuseID": 0,
      "FusePosition": 0,
      "LM_PinID": 0,
      "LM_PinPosition": 0,
      "LM_KnobID": 0,
      "LM_ButtonId": 0,
      "LM_FuseID": 0,
      "LM_FusePosition": 0,
      "Fault": 0,
      "Failure": 0,
      "PlayAudioClip_String3": false
    },
    {
      "Delivered": false,
      "Processed": false,
      "Completed": false,
      "Priority": false,
      "ID": "a9b590e8-cced-4218-83bc-ef672ab992c7",
      "Action": 0,
      "Timestamp": 25.0,
      "DisplayTime": 6.0,
      "From": 0,
      "Message": "선명하게 잘 들립니다, TEI 연소 완료했습니다.",
      "Value1": 0.0,
      "Value2": 0.0,
      "Value3": 0.0,
      "String1": "",
      "String2": "",
      "String3": "",
      "Bool1": false,
      "ThresholdLimit": 0.0,
      "PinID": 0,
      "PinPosition": 0,
      "KnobID": 0,
      "ButtonId": 0,
      "FuseID": 0,
      "FusePosition": 0,
      "LM_PinID": 0,
      "LM_PinPosition": 0,
      "LM_KnobID": 0,
      "LM_ButtonId": 0,
      "LM_FuseID": 0,
      "LM_FusePosition": 0,
      "Fault": 0,
      "Failure": 0,
      "PlayAudioClip_String3": false
    },
    {
      "Delivered": false,
      "Processed": false,
      "Completed": false,
      "Priority": false,
      "ID": "4541341c-6856-44be-8699-1498ac12de1a",
      "Action": 0,
      "Timestamp": 25.0,
      "DisplayTime": 6.0,
      "From": 2,
      "Message": "확인, 아주 잘했습니다! 우리는 지구를 향한 궤적에 올랐습니다. 다음 미션 단계에서는 중간 궤도 수정을 수행하고 지구에 착수할 것입니다.",
      "Value1": 0.0,
      "Value2": 0.0,
      "Value3": 0.0,
      "String1": "",
      "String2": "",
      "String3": "",
      "Bool1": false,
      "ThresholdLimit": 0.0,
      "PinID": 0,
      "PinPosition": 0,
      "KnobID": 0,
      "ButtonId": 0,
      "FuseID": 0,
      "FusePosition": 0,
      "LM_PinID": 0,
      "LM_PinPosition": 0,
      "LM_KnobID": 0,
      "LM_ButtonId": 0,
      "LM_FuseID": 0,
      "LM_FusePosition": 0,
      "Fault": 0,
      "Failure": 0,
      "PlayAudioClip_String3": false
    },
    {
      "Delivered": false,
      "Processed": false,
      "Completed": false,
      "Priority": false,
      "ID": "1b0aca51-9eae-4b2a-95bc-df6925ec29ce",
      "Action": 1004,
      "Timestamp": 25.0,
      "DisplayTime": 6.0,
      "From": 2,
      "Message": "경치를 즐기세요. (이것으로 미션이 완료됩니다)",
      "Value1": 0.0,
      "Value2": 0.0,
      "Value3": 0.0,
      "String1": "",
      "String2": "",
      "String3": "",
      "Bool1": false,
      "ThresholdLimit": 0.0,
      "PinID": 0,
      "PinPosition": 0,
      "KnobID": 0,
      "ButtonId": 0,
      "FuseID": 0,
      "FusePosition": 0,
      "LM_PinID": 0,
      "LM_PinPosition": 0,
      "LM_KnobID": 0,
      "LM_ButtonId": 0,
      "LM_FuseID": 0,
      "LM_FusePosition": 0,
      "Fault": 0,
      "Failure": 0,
      "PlayAudioClip_String3": false
    }
  ],
  "MissionGoals": [
    {
      "Progress": null,
      "Completed": false,
      "Type": 0,
      "Description": "미션을 완료하세요",
      "Target1": 0.0,
      "Target2": 0.0,
      "Target3": 0.0,
      "String1": "",
      "String2": ""
    }
  ],
  "MissionActivities": [],
  "MissionChecklists": [],
  "Comment": "",
  "SpaceProgram": 2,
  "Id": 5577448,
  "ID": "6ad20daa-69b5-4de7-a595-ca32860fbc4d",
  "Title": "THRUST OF THE ENGINEERS",
  "Description": "이제 귀환할 시간입니다. 승무원은 달 궤도에 있으며, 지구로 돌아가는 귀환 궤적에 오르기 위해 지구 귀환 궤도 진입(TEI) 연소를 준비해야 합니다.",
  "BriefingText": "현재 달 궤도를 완료하고 지구 귀환 궤도 진입(TEI) 연소를 계획한 뒤, 지구를 향한 여정을 시작하세요.",
  "FlightPlanPrefabId": 0,
  "MinutesBeforeLaunch": 60.0,
  "TargetAp": 0.0,
  "TargetPe": 0.0,
  "Inclination": 28.91,
  "DeltaRoll": 75.5,
  "CommandModulePilot": "AARON",
  "LunarModulePilot": "LODKINS",
  "DisableDefaultAudioSFX": false,
  "LoadState": "StateM5.json",
  "EarthRotationOffsetDegrees": 0.0,
  "Payload": 0,
  "AllowRandomFailures": false,
  "RealisticRadioRange": false,
  "OverrideSunPhase": false,
  "OverrideSunPhaseValue": 180.0,
  "OverridePanelStateCM": false,
  "OverridePanelStateFileNameCM": "Default/Ingress.json",
  "OverridePanelStateLM": false,
  "OverridePanelStateFileNameLM": "Default/Ingress.json",
  "AlwaysSyncMissionCycleTimerWithMET": false
}