{
  "LV": 0,
  "StartInOrbit": true,
  "ScheduledLaunchTime": "1969-07-16T13:32:00",
  "InitialTimeToRetrograde": "6.06:00:00",
  "MissionCommands": [
    {
      "Delivered": false,
      "Processed": false,
      "Completed": false,
      "Priority": false,
      "ID": "9d2b1c61-995d-40f1-b9ec-676dc1d0c51b",
      "Action": 0,
      "Timestamp": 25.0,
      "DisplayTime": 6.0,
      "From": 0,
      "Message": "좋습니다 {{cmp}}, {{lmp}}, 이제 일어날 시간입니다, 곧 하강 궤도 진입(DOI) 연소 계획을 시작할 것입니다.",
      "Value1": 0.0,
      "Value2": 0.0,
      "Value3": 0.0,
      "String1": "",
      "String2": "",
      "String3": "",
      "Bool1": false,
      "ThresholdLimit": 0.0,
      "PinID": 0,
      "PinPosition": 0,
      "KnobID": 0,
      "ButtonId": 0,
      "FuseID": 0,
      "FusePosition": 0,
      "LM_PinID": 0,
      "LM_PinPosition": 0,
      "LM_KnobID": 0,
      "LM_ButtonId": 0,
      "LM_FuseID": 0,
      "LM_FusePosition": 0,
      "Fault": 0,
      "Failure": 0,
      "PlayAudioClip_String3": false
    },
    {
      "Delivered": false,
      "Processed": false,
      "Completed": false,
      "Priority": false,
      "ID": "d14703b9-a44c-4e5f-b68e-3bd4443ceb50",
      "Action": 0,
      "Timestamp": 25.0,
      "DisplayTime": 6.0,
      "From": 1,
      "Message": "확인, 어차피 잠은 별로 못 잤습니다, 이 달의 경치에 너무 흥분해서요.",
      "Value1": 0.0,
      "Value2": 0.0,
      "Value3": 0.0,
      "String1": "",
      "String2": "",
      "String3": "",
      "Bool1": false,
      "ThresholdLimit": 0.0,
      "PinID": 0,
      "PinPosition": 0,
      "KnobID": 0,
      "ButtonId": 0,
      "FuseID": 0,
      "FusePosition": 0,
      "LM_PinID": 0,
      "LM_PinPosition": 0,
      "LM_KnobID": 0,
      "LM_ButtonId": 0,
      "LM_FuseID": 0,
      "LM_FusePosition": 0,
      "Fault": 0,
      "Failure": 0,
      "PlayAudioClip_String3": false
    },
    {
      "Delivered": false,
      "Processed": false,
      "Completed": false,
      "Priority": false,
      "ID": "4d5ead98-6ec5-4120-9c4a-7ea3d67663db",
      "Action": 0,
      "Timestamp": 25.0,
      "DisplayTime": 6.0,
      "From": 3,
      "Message": "네, 저기로 내려가 봅시다.",
      "Value1": 0.0,
      "Value2": 0.0,
      "Value3": 0.0,
      "String1": "",
      "String2": "",
      "String3": "",
      "Bool1": false,
      "ThresholdLimit": 0.0,
      "PinID": 0,
      "PinPosition": 0,
      "KnobID": 0,
      "ButtonId": 0,
      "FuseID": 0,
      "FusePosition": 0,
      "LM_PinID": 0,
      "LM_PinPosition": 0,
      "LM_KnobID": 0,
      "LM_ButtonId": 0,
      "LM_FuseID": 0,
      "LM_FusePosition": 0,
      "Fault": 0,
      "Failure": 0,
      "PlayAudioClip_String3": false
    },
    {
      "Delivered": false,
      "Processed": false,
      "Completed": false,
      "Priority": false,
      "ID": "d31803cf-080c-4f23-b3d7-a495b24a5b71",
      "Action": 0,
      "Timestamp": 25.0,
      "DisplayTime": 6.0,
      "From": 0,
      "Message": "확인. 고요의 바다 전방에서 근지점(Pe)을 낮추는 연소를 계획하겠습니다.",
      "Value1": 0.0,
      "Value2": 0.0,
      "Value3": 0.0,
      "String1": "",
      "String2": "",
      "String3": "",
      "Bool1": false,
      "ThresholdLimit": 0.0,
      "PinID": 0,
      "PinPosition": 0,
      "KnobID": 0,
      "ButtonId": 0,
      "FuseID": 0,
      "FusePosition": 0,
      "LM_PinID": 0,
      "LM_PinPosition": 0,
      "LM_KnobID": 0,
      "LM_ButtonId": 0,
      "LM_FuseID": 0,
      "LM_FusePosition": 0,
      "Fault": 0,
      "Failure": 0,
      "PlayAudioClip_String3": false
    },
    {
      "Delivered": false,
      "Processed": false,
      "Completed": false,
      "Priority": false,
      "ID": "34dd9c1a-cbda-4a4a-8bf1-a48ce986ebf2",
      "Action": 757,
      "Timestamp": 25.0,
      "DisplayTime": 6.0,
      "From": 1,
      "Message": "확인, 연소 계획기를 여세요. 원하는 지역에 착륙할 수 있도록 연소를 계획하는 몇 가지 요령을 살펴보겠습니다.",
      "Value1": 0.0,
      "Value2": 0.0,
      "Value3": 0.0,
      "String1": "",
      "String2": "",
      "String3": "",
      "Bool1": false,
      "ThresholdLimit": 0.0,
      "PinID": 0,
      "PinPosition": 0,
      "KnobID": 0,
      "ButtonId": 0,
      "FuseID": 0,
      "FusePosition": 0,
      "LM_PinID": 0,
      "LM_PinPosition": 0,
      "LM_KnobID": 0,
      "LM_ButtonId": 0,
      "LM_FuseID": 0,
      "LM_FusePosition": 0,
      "Fault": 0,
      "Failure": 0,
      "PlayAudioClip_String3": false
    },
    {
      "Delivered": false,
      "Processed": false,
      "Completed": false,
      "Priority": false,
      "ID": "a40380ea-800f-4ed6-a020-243f96e49650",
      "Action": 0,
      "Timestamp": 25.0,
      "DisplayTime": 6.0,
      "From": 1,
      "Message": "Phase를 250으로 설정하고, dV는 71 fps 역행 방향으로 설정한 뒤 연소 계획기를 닫으세요. 미션 패드에서 MAP을 열고 Moon을 선택하세요. 초록색 TIG 커서의 위치를 확인하세요.",
      "Value1": 0.0,
      "Value2": 0.0,
      "Value3": 0.0,
      "String1": "",
      "String2": "",
      "String3": "",
      "Bool1": false,
      "ThresholdLimit": 0.0,
      "PinID": 0,
      "PinPosition": 0,
      "KnobID": 0,
      "ButtonId": 0,
      "FuseID": 0,
      "FusePosition": 0,
      "LM_PinID": 0,
      "LM_PinPosition": 0,
      "LM_KnobID": 0,
      "LM_ButtonId": 0,
      "LM_FuseID": 0,
      "LM_FusePosition": 0,
      "Fault": 0,
      "Failure": 0,
      "PlayAudioClip_String3": false
    },
    {
      "Delivered": false,
      "Processed": false,
      "Completed": false,
      "Priority": false,
      "ID": "9b111aa1-559a-4d49-9f5a-0e683c21c493",
      "Action": 0,
      "Timestamp": 25.0,
      "DisplayTime": 6.0,
      "From": 0,
      "Message": "고요의 바다에 착륙하려면 Pe가 바로 이 위치에 있어야 합니다.",
      "Value1": 0.0,
      "Value2": 0.0,
      "Value3": 0.0,
      "String1": "",
      "String2": "",
      "String3": "",
      "Bool1": false,
      "ThresholdLimit": 0.0,
      "PinID": 0,
      "PinPosition": 0,
      "KnobID": 0,
      "ButtonId": 0,
      "FuseID": 0,
      "FusePosition": 0,
      "LM_PinID": 0,
      "LM_PinPosition": 0,
      "LM_KnobID": 0,
      "LM_ButtonId": 0,
      "LM_FuseID": 0,
      "LM_FusePosition": 0,
      "Fault": 0,
      "Failure": 0,
      "PlayAudioClip_String3": false
    },
    {
      "Delivered": false,
      "Processed": false,
      "Completed": false,
      "Priority": false,
      "ID": "f4ecc3b5-c068-4034-9af1-c42fa2711eb1",
      "Action": 0,
      "Timestamp": 25.0,
      "DisplayTime": 6.0,
      "From": 0,
      "Message": "하지만 250도에서 연소하면 Pe는 달 반대편에 위치하게 됩니다. 이를 바로잡으려면 250에서 180도를 빼세요. 그러면 70이 되므로 phase를 70으로 설정하세요.",
      "Value1": 0.0,
      "Value2": 0.0,
      "Value3": 0.0,
      "String1": "",
      "String2": "",
      "String3": "",
      "Bool1": false,
      "ThresholdLimit": 0.0,
      "PinID": 0,
      "PinPosition": 0,
      "KnobID": 0,
      "ButtonId": 0,
      "FuseID": 0,
      "FusePosition": 0,
      "LM_PinID": 0,
      "LM_PinPosition": 0,
      "LM_KnobID": 0,
      "LM_ButtonId": 0,
      "LM_FuseID": 0,
      "LM_FusePosition": 0,
      "Fault": 0,
      "Failure": 0,
      "PlayAudioClip_String3": false
    },
    {
      "Delivered": false,
      "Processed": false,
      "Completed": false,
      "Priority": false,
      "ID": "e09333ff-9ec7-4d94-a385-ff38db4183f4",
      "Action": 758,
      "Timestamp": 25.0,
      "DisplayTime": 6.0,
      "From": 1,
      "Message": "phase를 70으로 설정하면 연소가 올바른 위치에서 Pe를 낮추게 됩니다. 필요하면 값을 자유롭게 조정하고, 준비되면 REQUEST를 누르세요.",
      "Value1": 0.0,
      "Value2": 0.0,
      "Value3": 0.0,
      "String1": "",
      "String2": "",
      "String3": "",
      "Bool1": false,
      "ThresholdLimit": 0.0,
      "PinID": 0,
      "PinPosition": 0,
      "KnobID": 0,
      "ButtonId": 0,
      "FuseID": 0,
      "FusePosition": 0,
      "LM_PinID": 0,
      "LM_PinPosition": 0,
      "LM_KnobID": 0,
      "LM_ButtonId": 0,
      "LM_FuseID": 0,
      "LM_FusePosition": 0,
      "Fault": 0,
      "Failure": 0,
      "PlayAudioClip_String3": false
    },
    {
      "Delivered": false,
      "Processed": false,
      "Completed": false,
      "Priority": false,
      "ID": "26d9fdd7-0700-4734-b2fe-34c2958b861f",
      "Action": 0,
      "Timestamp": 25.0,
      "DisplayTime": 6.0,
      "From": 0,
      "Message": "확인, 연소를 준비합시다.",
      "Value1": 0.0,
      "Value2": 0.0,
      "Value3": 0.0,
      "String1": "",
      "String2": "",
      "String3": "",
      "Bool1": false,
      "ThresholdLimit": 0.0,
      "PinID": 0,
      "PinPosition": 0,
      "KnobID": 0,
      "ButtonId": 0,
      "FuseID": 0,
      "FusePosition": 0,
      "LM_PinID": 0,
      "LM_PinPosition": 0,
      "LM_KnobID": 0,
      "LM_ButtonId": 0,
      "LM_FuseID": 0,
      "LM_FusePosition": 0,
      "Fault": 0,
      "Failure": 0,
      "PlayAudioClip_String3": false
    },
    {
      "Delivered": false,
      "Processed": false,
      "Completed": false,
      "Priority": false,
      "ID": "a4ae3bf4-e89b-405f-b9e1-ccadf11edaeb",
      "Action": 204,
      "Timestamp": 25.0,
      "DisplayTime": 6.0,
      "From": 1,
      "Message": "P30을 실행해 연소를 설정한 다음, 카운트다운이 보일 때까지 PRO를 누르세요.",
      "Value1": 30.0,
      "Value2": 0.0,
      "Value3": 0.0,
      "String1": "",
      "String2": "",
      "String3": "",
      "Bool1": false,
      "ThresholdLimit": 0.0,
      "PinID": 0,
      "PinPosition": 0,
      "KnobID": 0,
      "ButtonId": 0,
      "FuseID": 0,
      "FusePosition": 0,
      "LM_PinID": 0,
      "LM_PinPosition": 0,
      "LM_KnobID": 0,
      "LM_ButtonId": 0,
      "LM_FuseID": 0,
      "LM_FusePosition": 0,
      "Fault": 0,
      "Failure": 0,
      "PlayAudioClip_String3": false
    },
    {
      "Delivered": false,
      "Processed": false,
      "Completed": false,
      "Priority": false,
      "ID": "4fc7355d-44fd-4586-851e-56a49ee5ef37",
      "Action": 0,
      "Timestamp": 25.0,
      "DisplayTime": 6.0,
      "From": 0,
      "Message": "확인, 그렇게 하겠습니다.",
      "Value1": 0.0,
      "Value2": 0.0,
      "Value3": 0.0,
      "String1": "",
      "String2": "",
      "String3": "",
      "Bool1": false,
      "ThresholdLimit": 0.0,
      "PinID": 0,
      "PinPosition": 0,
      "KnobID": 0,
      "ButtonId": 0,
      "FuseID": 0,
      "FusePosition": 0,
      "LM_PinID": 0,
      "LM_PinPosition": 0,
      "LM_KnobID": 0,
      "LM_ButtonId": 0,
      "LM_FuseID": 0,
      "LM_FusePosition": 0,
      "Fault": 0,
      "Failure": 0,
      "PlayAudioClip_String3": false
    },
    {
      "Delivered": false,
      "Processed": false,
      "Completed": false,
      "Priority": false,
      "ID": "a9612c5c-1558-41d3-80cf-6adc852b56d3",
      "Action": 18,
      "Timestamp": 25.0,
      "DisplayTime": 6.0,
      "From": 1,
      "Message": "카운트다운이 보이면 T -20분으로 타임스케일을 사용하세요.",
      "Value1": 1200.0,
      "Value2": 0.0,
      "Value3": 0.0,
      "String1": "",
      "String2": "",
      "String3": "",
      "Bool1": false,
      "ThresholdLimit": 0.0,
      "PinID": 0,
      "PinPosition": 0,
      "KnobID": 0,
      "ButtonId": 0,
      "FuseID": 0,
      "FusePosition": 0,
      "LM_PinID": 0,
      "LM_PinPosition": 0,
      "LM_KnobID": 0,
      "LM_ButtonId": 0,
      "LM_FuseID": 0,
      "LM_FusePosition": 0,
      "Fault": 0,
      "Failure": 0,
      "PlayAudioClip_String3": false
    },
    {
      "Delivered": false,
      "Processed": false,
      "Completed": false,
      "Priority": false,
      "ID": "534d45d6-71b7-4ee5-96bc-194cda27c89d",
      "Action": 0,
      "Timestamp": 25.0,
      "DisplayTime": 6.0,
      "From": 0,
      "Message": "DOI 연소까지 T -20분.",
      "Value1": 0.0,
      "Value2": 0.0,
      "Value3": 0.0,
      "String1": "",
      "String2": "",
      "String3": "",
      "Bool1": false,
      "ThresholdLimit": 0.0,
      "PinID": 0,
      "PinPosition": 0,
      "KnobID": 0,
      "ButtonId": 0,
      "FuseID": 0,
      "FusePosition": 0,
      "LM_PinID": 0,
      "LM_PinPosition": 0,
      "LM_KnobID": 0,
      "LM_ButtonId": 0,
      "LM_FuseID": 0,
      "LM_FusePosition": 0,
      "Fault": 0,
      "Failure": 0,
      "PlayAudioClip_String3": false
    },
    {
      "Delivered": false,
      "Processed": false,
      "Completed": false,
      "Priority": false,
      "ID": "3517a830-890a-4320-99ee-545d184950f7",
      "Action": 204,
      "Timestamp": 25.0,
      "DisplayTime": 6.0,
      "From": 1,
      "Message": "확인, P00이 될 때까지 PRO를 누른 다음 P52를 실행하세요.",
      "Value1": 52.0,
      "Value2": 0.0,
      "Value3": 0.0,
      "String1": "",
      "String2": "",
      "String3": "",
      "Bool1": false,
      "ThresholdLimit": 0.0,
      "PinID": 0,
      "PinPosition": 0,
      "KnobID": 0,
      "ButtonId": 0,
      "FuseID": 0,
      "FusePosition": 0,
      "LM_PinID": 0,
      "LM_PinPosition": 0,
      "LM_KnobID": 0,
      "LM_ButtonId": 0,
      "LM_FuseID": 0,
      "LM_FusePosition": 0,
      "Fault": 0,
      "Failure": 0,
      "PlayAudioClip_String3": false
    },
    {
      "Delivered": false,
      "Processed": false,
      "Completed": false,
      "Priority": false,
      "ID": "b196267b-24ba-4a38-80ec-12331907e401",
      "Action": 204,
      "Timestamp": 25.0,
      "DisplayTime": 6.0,
      "From": 1,
      "Message": "좋습니다, P52. 로드되면 V22E +00001E, PRO, PRO를 입력해 플랫폼을 원하는 연소 방향으로 정렬하세요.",
      "Value1": 0.0,
      "Value2": 0.0,
      "Value3": 0.0,
      "String1": "",
      "String2": "",
      "String3": "",
      "Bool1": false,
      "ThresholdLimit": 0.0,
      "PinID": 0,
      "PinPosition": 0,
      "KnobID": 0,
      "ButtonId": 0,
      "FuseID": 0,
      "FusePosition": 0,
      "LM_PinID": 0,
      "LM_PinPosition": 0,
      "LM_KnobID": 0,
      "LM_ButtonId": 0,
      "LM_FuseID": 0,
      "LM_FusePosition": 0,
      "Fault": 0,
      "Failure": 0,
      "PlayAudioClip_String3": false
    },
    {
      "Delivered": false,
      "Processed": false,
      "Completed": false,
      "Priority": false,
      "ID": "8140a448-377b-49f2-96da-4834c823d400",
      "Action": 0,
      "Timestamp": 25.0,
      "DisplayTime": 6.0,
      "From": 0,
      "Message": "IMU가 원하는 연소 방향으로 정렬되었습니다.",
      "Value1": 0.0,
      "Value2": 0.0,
      "Value3": 0.0,
      "String1": "",
      "String2": "",
      "String3": "",
      "Bool1": false,
      "ThresholdLimit": 0.0,
      "PinID": 0,
      "PinPosition": 0,
      "KnobID": 0,
      "ButtonId": 0,
      "FuseID": 0,
      "FusePosition": 0,
      "LM_PinID": 0,
      "LM_PinPosition": 0,
      "LM_KnobID": 0,
      "LM_ButtonId": 0,
      "LM_FuseID": 0,
      "LM_FusePosition": 0,
      "Fault": 0,
      "Failure": 0,
      "PlayAudioClip_String3": false
    },
    {
      "Delivered": false,
      "Processed": false,
      "Completed": false,
      "Priority": false,
      "ID": "b5a2fc52-1e99-43df-8e59-90072738af70",
      "Action": 0,
      "Timestamp": 25.0,
      "DisplayTime": 6.0,
      "From": 0,
      "Message": "확인, 그런 다음 V49E를 입력하고 자동 기동 루틴을 완료하세요.",
      "Value1": 0.0,
      "Value2": 0.0,
      "Value3": 0.0,
      "String1": "",
      "String2": "",
      "String3": "",
      "Bool1": false,
      "ThresholdLimit": 0.0,
      "PinID": 0,
      "PinPosition": 0,
      "KnobID": 0,
      "ButtonId": 0,
      "FuseID": 0,
      "FusePosition": 0,
      "LM_PinID": 0,
      "LM_PinPosition": 0,
      "LM_KnobID": 0,
      "LM_ButtonId": 0,
      "LM_FuseID": 0,
      "LM_FusePosition": 0,
      "Fault": 0,
      "Failure": 0,
      "PlayAudioClip_String3": false
    },
    {
      "Delivered": false,
      "Processed": false,
      "Completed": false,
      "Priority": false,
      "ID": "81e901a9-08d2-4189-9739-5245a691d317",
      "Action": 204,
      "Timestamp": 25.0,
      "DisplayTime": 6.0,
      "From": 1,
      "Message": "좋습니다, 그런 다음 (P40) G&N SPS THRUSTING 절차를 사용해 연소를 준비하세요. 준비되면 타임스케일을 자유롭게 사용하되, 올바른 자세를 잡을 충분한 시간을 확보하세요.",
      "Value1": 40.0,
      "Value2": 0.0,
      "Value3": 0.0,
      "String1": "",
      "String2": "",
      "String3": "",
      "Bool1": false,
      "ThresholdLimit": 0.0,
      "PinID": 0,
      "PinPosition": 0,
      "KnobID": 0,
      "ButtonId": 0,
      "FuseID": 0,
      "FusePosition": 0,
      "LM_PinID": 0,
      "LM_PinPosition": 0,
      "LM_KnobID": 0,
      "LM_ButtonId": 0,
      "LM_FuseID": 0,
      "LM_FusePosition": 0,
      "Fault": 0,
      "Failure": 0,
      "PlayAudioClip_String3": false
    },
    {
      "Delivered": false,
      "Processed": false,
      "Completed": false,
      "Priority": false,
      "ID": "ab5da4de-4cfd-432f-9a92-e8a7fa34022b",
      "Action": 18,
      "Timestamp": 25.0,
      "DisplayTime": 6.0,
      "From": 0,
      "Message": "확인, P40, 연소를 설정하고 점화를 준비하겠습니다.",
      "Value1": 60.0,
      "Value2": 0.0,
      "Value3": 0.0,
      "String1": "",
      "String2": "",
      "String3": "",
      "Bool1": false,
      "ThresholdLimit": 0.0,
      "PinID": 0,
      "PinPosition": 0,
      "KnobID": 0,
      "ButtonId": 0,
      "FuseID": 0,
      "FusePosition": 0,
      "LM_PinID": 0,
      "LM_PinPosition": 0,
      "LM_KnobID": 0,
      "LM_ButtonId": 0,
      "LM_FuseID": 0,
      "LM_FusePosition": 0,
      "Fault": 0,
      "Failure": 0,
      "PlayAudioClip_String3": false
    },
    {
      "Delivered": false,
      "Processed": false,
      "Completed": false,
      "Priority": false,
      "ID": "3cd41275-dfad-47b3-b14d-141c9730d74e",
      "Action": 0,
      "Timestamp": 25.0,
      "DisplayTime": 6.0,
      "From": 0,
      "Message": "DOI 연소까지 T -60초. ",
      "Value1": 0.0,
      "Value2": 0.0,
      "Value3": 0.0,
      "String1": "",
      "String2": "",
      "String3": "",
      "Bool1": false,
      "ThresholdLimit": 0.0,
      "PinID": 0,
      "PinPosition": 0,
      "KnobID": 0,
      "ButtonId": 0,
      "FuseID": 0,
      "FusePosition": 0,
      "LM_PinID": 0,
      "LM_PinPosition": 0,
      "LM_KnobID": 0,
      "LM_ButtonId": 0,
      "LM_FuseID": 0,
      "LM_FusePosition": 0,
      "Fault": 0,
      "Failure": 0,
      "PlayAudioClip_String3": false
    },
    {
      "Delivered": false,
      "Processed": false,
      "Completed": false,
      "Priority": false,
      "ID": "02379ded-1dbe-42da-a4d8-727db7aa7df1",
      "Action": 164,
      "Timestamp": 25.0,
      "DisplayTime": 6.0,
      "From": 1,
      "Message": "확인, 짧은 연소가 될 것입니다.",
      "Value1": 0.0,
      "Value2": 0.0,
      "Value3": 0.0,
      "String1": "",
      "String2": "",
      "String3": "",
      "Bool1": false,
      "ThresholdLimit": 0.0,
      "PinID": 0,
      "PinPosition": 0,
      "KnobID": 0,
      "ButtonId": 0,
      "FuseID": 0,
      "FusePosition": 0,
      "LM_PinID": 0,
      "LM_PinPosition": 0,
      "LM_KnobID": 0,
      "LM_ButtonId": 0,
      "LM_FuseID": 0,
      "LM_FusePosition": 0,
      "Fault": 0,
      "Failure": 0,
      "PlayAudioClip_String3": false
    },
    {
      "Delivered": false,
      "Processed": false,
      "Completed": false,
      "Priority": false,
      "ID": "1d84a83d-c228-4297-a557-e482780a1361",
      "Action": 165,
      "Timestamp": 25.0,
      "DisplayTime": 6.0,
      "From": 0,
      "Message": "점화.",
      "Value1": 0.0,
      "Value2": 0.0,
      "Value3": 0.0,
      "String1": "",
      "String2": "",
      "String3": "",
      "Bool1": false,
      "ThresholdLimit": 0.0,
      "PinID": 0,
      "PinPosition": 0,
      "KnobID": 0,
      "ButtonId": 0,
      "FuseID": 0,
      "FusePosition": 0,
      "LM_PinID": 0,
      "LM_PinPosition": 0,
      "LM_KnobID": 0,
      "LM_ButtonId": 0,
      "LM_FuseID": 0,
      "LM_FusePosition": 0,
      "Fault": 0,
      "Failure": 0,
      "PlayAudioClip_String3": false
    },
    {
      "Delivered": false,
      "Processed": false,
      "Completed": false,
      "Priority": false,
      "ID": "07a1e5ba-822c-47d1-b55c-b4a068c2c1d0",
      "Action": 0,
      "Timestamp": 25.0,
      "DisplayTime": 6.0,
      "From": 0,
      "Message": "컷오프!",
      "Value1": 0.0,
      "Value2": 0.0,
      "Value3": 0.0,
      "String1": "",
      "String2": "",
      "String3": "",
      "Bool1": false,
      "ThresholdLimit": 0.0,
      "PinID": 0,
      "PinPosition": 0,
      "KnobID": 0,
      "ButtonId": 0,
      "FuseID": 0,
      "FusePosition": 0,
      "LM_PinID": 0,
      "LM_PinPosition": 0,
      "LM_KnobID": 0,
      "LM_ButtonId": 0,
      "LM_FuseID": 0,
      "LM_FusePosition": 0,
      "Fault": 0,
      "Failure": 0,
      "PlayAudioClip_String3": false
    },
    {
      "Delivered": false,
      "Processed": false,
      "Completed": false,
      "Priority": false,
      "ID": "3551cc78-562a-4a60-ba1a-e49dcac6371e",
      "Action": 11,
      "Timestamp": 25.0,
      "DisplayTime": 6.0,
      "From": 1,
      "Message": "확인! MAP 화면을 확인하고 Pe의 최소 고도가 5.4 nmi인지 확인하세요. 그보다 낮으면 RCS와 병진 컨트롤을 사용해 수동으로 수정하세요.",
      "Value1": 11.0,
      "Value2": 0.0,
      "Value3": 0.0,
      "String1": "",
      "String2": "",
      "String3": "",
      "Bool1": false,
      "ThresholdLimit": 0.0,
      "PinID": 0,
      "PinPosition": 0,
      "KnobID": 0,
      "ButtonId": 0,
      "FuseID": 0,
      "FusePosition": 0,
      "LM_PinID": 0,
      "LM_PinPosition": 0,
      "LM_KnobID": 0,
      "LM_ButtonId": 0,
      "LM_FuseID": 0,
      "LM_FusePosition": 0,
      "Fault": 0,
      "Failure": 0,
      "PlayAudioClip_String3": false
    },
    {
      "Delivered": false,
      "Processed": false,
      "Completed": false,
      "Priority": false,
      "ID": "ffff7b42-1f85-4f49-9bbf-f4f2352c8b6a",
      "Action": 0,
      "Timestamp": 25.0,
      "DisplayTime": 6.0,
      "From": 0,
      "Message": "Pe는 정상입니다. 달착륙선을 준비합시다. 활성화가 필요합니다.",
      "Value1": 0.0,
      "Value2": 0.0,
      "Value3": 0.0,
      "String1": "",
      "String2": "",
      "String3": "",
      "Bool1": false,
      "ThresholdLimit": 0.0,
      "PinID": 0,
      "PinPosition": 0,
      "KnobID": 0,
      "ButtonId": 0,
      "FuseID": 0,
      "FusePosition": 0,
      "LM_PinID": 0,
      "LM_PinPosition": 0,
      "LM_KnobID": 0,
      "LM_ButtonId": 0,
      "LM_FuseID": 0,
      "LM_FusePosition": 0,
      "Fault": 0,
      "Failure": 0,
      "PlayAudioClip_String3": false
    },
    {
      "Delivered": false,
      "Processed": false,
      "Completed": false,
      "Priority": false,
      "ID": "e76770a6-253a-4292-b63c-f2bdf211f6ae",
      "Action": 3109,
      "Timestamp": 25.0,
      "DisplayTime": 6.0,
      "From": 3,
      "Message": "확인, 시작합시다. 달착륙선 활성화 체크리스트를 사용해 일반 진입 및 활성화 절차를 따르고, 완료되면 보고하세요.",
      "Value1": 0.0,
      "Value2": 0.0,
      "Value3": 0.0,
      "String1": "",
      "String2": "",
      "String3": "",
      "Bool1": false,
      "ThresholdLimit": 0.0,
      "PinID": 0,
      "PinPosition": 0,
      "KnobID": 0,
      "ButtonId": 0,
      "FuseID": 0,
      "FusePosition": 0,
      "LM_PinID": 0,
      "LM_PinPosition": 0,
      "LM_KnobID": 0,
      "LM_ButtonId": 0,
      "LM_FuseID": 0,
      "LM_FusePosition": 0,
      "Fault": 0,
      "Failure": 0,
      "PlayAudioClip_String3": false
    },
    {
      "Delivered": false,
      "Processed": false,
      "Completed": false,
      "Priority": false,
      "ID": "a58d2830-2c89-4a36-90d2-ea1c1288f145",
      "Action": 0,
      "Timestamp": 25.0,
      "DisplayTime": 6.0,
      "From": 0,
      "Message": "착륙 다리가 전개되었습니다.",
      "Value1": 0.0,
      "Value2": 0.0,
      "Value3": 0.0,
      "String1": "",
      "String2": "",
      "String3": "",
      "Bool1": false,
      "ThresholdLimit": 0.0,
      "PinID": 0,
      "PinPosition": 0,
      "KnobID": 0,
      "ButtonId": 0,
      "FuseID": 0,
      "FusePosition": 0,
      "LM_PinID": 0,
      "LM_PinPosition": 0,
      "LM_KnobID": 0,
      "LM_ButtonId": 0,
      "LM_FuseID": 0,
      "LM_FusePosition": 0,
      "Fault": 0,
      "Failure": 0,
      "PlayAudioClip_String3": false
    },
    {
      "Delivered": false,
      "Processed": false,
      "Completed": false,
      "Priority": false,
      "ID": "d7c3edf5-9bac-4c3f-88f4-fa79dacf011a",
      "Action": 1,
      "Timestamp": 25.0,
      "DisplayTime": 6.0,
      "From": 3,
      "Message": "확인. 시스템을 확인하고 다음으로 넘어갈 준비가 되면 PROCEED를 누르세요.",
      "Value1": 0.0,
      "Value2": 0.0,
      "Value3": 0.0,
      "String1": "PROCEED",
      "String2": "",
      "String3": "",
      "Bool1": false,
      "ThresholdLimit": 0.0,
      "PinID": 0,
      "PinPosition": 0,
      "KnobID": 0,
      "ButtonId": 0,
      "FuseID": 0,
      "FusePosition": 0,
      "LM_PinID": 0,
      "LM_PinPosition": 0,
      "LM_KnobID": 0,
      "LM_ButtonId": 0,
      "LM_FuseID": 0,
      "LM_FusePosition": 0,
      "Fault": 0,
      "Failure": 0,
      "PlayAudioClip_String3": false
    },
    {
      "Delivered": false,
      "Processed": false,
      "Completed": false,
      "Priority": false,
      "ID": "c476b90b-bd7e-4593-8f96-26927156f681",
      "Action": 0,
      "Timestamp": 25.0,
      "DisplayTime": 6.0,
      "From": 0,
      "Message": "시스템 확인 완료, 진행해도 좋을 것 같습니다.",
      "Value1": 0.0,
      "Value2": 0.0,
      "Value3": 0.0,
      "String1": "",
      "String2": "",
      "String3": "",
      "Bool1": false,
      "ThresholdLimit": 0.0,
      "PinID": 0,
      "PinPosition": 0,
      "KnobID": 0,
      "ButtonId": 0,
      "FuseID": 0,
      "FusePosition": 0,
      "LM_PinID": 0,
      "LM_PinPosition": 0,
      "LM_KnobID": 0,
      "LM_ButtonId": 0,
      "LM_FuseID": 0,
      "LM_FusePosition": 0,
      "Fault": 0,
      "Failure": 0,
      "PlayAudioClip_String3": false
    },
    {
      "Delivered": false,
      "Processed": false,
      "Completed": false,
      "Priority": false,
      "ID": "a8b9193e-7e79-4ae5-b044-b0a8c09e06cf",
      "Action": 0,
      "Timestamp": 25.0,
      "DisplayTime": 6.0,
      "From": 3,
      "Message": "확인. Pe에 도달하면 도킹을 해제하겠습니다.",
      "Value1": 0.0,
      "Value2": 0.0,
      "Value3": 0.0,
      "String1": "",
      "String2": "",
      "String3": "",
      "Bool1": false,
      "ThresholdLimit": 0.0,
      "PinID": 0,
      "PinPosition": 0,
      "KnobID": 0,
      "ButtonId": 0,
      "FuseID": 0,
      "FusePosition": 0,
      "LM_PinID": 0,
      "LM_PinPosition": 0,
      "LM_KnobID": 0,
      "LM_ButtonId": 0,
      "LM_FuseID": 0,
      "LM_FusePosition": 0,
      "Fault": 0,
      "Failure": 0,
      "PlayAudioClip_String3": false
    },
    {
      "Delivered": false,
      "Processed": false,
      "Completed": false,
      "Priority": false,
      "ID": "40221e78-fcde-4dad-96c3-ae3eff8d06bb",
      "Action": 15,
      "Timestamp": 25.0,
      "DisplayTime": 6.0,
      "From": 0,
      "Message": "확인, Pe에서 도킹 해제합니다, 활성화 절차 후에는 한숨 돌리고, 도킹 해제와 동력 하강 준비 전에 잠시 휴식을 취합시다.",
      "Value1": 120.0,
      "Value2": 0.0,
      "Value3": 0.0,
      "String1": "",
      "String2": "",
      "String3": "",
      "Bool1": false,
      "ThresholdLimit": 0.0,
      "PinID": 0,
      "PinPosition": 0,
      "KnobID": 0,
      "ButtonId": 0,
      "FuseID": 0,
      "FusePosition": 0,
      "LM_PinID": 0,
      "LM_PinPosition": 0,
      "LM_KnobID": 0,
      "LM_ButtonId": 0,
      "LM_FuseID": 0,
      "LM_FusePosition": 0,
      "Fault": 0,
      "Failure": 0,
      "PlayAudioClip_String3": false
    },
    {
      "Delivered": false,
      "Processed": false,
      "Completed": false,
      "Priority": false,
      "ID": "a07585fa-e017-4edf-8158-09d8859e54ac",
      "Action": 0,
      "Timestamp": 25.0,
      "DisplayTime": 6.0,
      "From": 0,
      "Message": "도킹 해제까지 T -2분.",
      "Value1": 0.0,
      "Value2": 0.0,
      "Value3": 0.0,
      "String1": "",
      "String2": "",
      "String3": "",
      "Bool1": false,
      "ThresholdLimit": 0.0,
      "PinID": 0,
      "PinPosition": 0,
      "KnobID": 0,
      "ButtonId": 0,
      "FuseID": 0,
      "FusePosition": 0,
      "LM_PinID": 0,
      "LM_PinPosition": 0,
      "LM_KnobID": 0,
      "LM_ButtonId": 0,
      "LM_FuseID": 0,
      "LM_FusePosition": 0,
      "Fault": 0,
      "Failure": 0,
      "PlayAudioClip_String3": false
    },
    {
      "Delivered": false,
      "Processed": false,
      "Completed": false,
      "Priority": false,
      "ID": "bb15beaa-7c12-491c-8960-a4c76342f1cf",
      "Action": 1,
      "Timestamp": 25.0,
      "DisplayTime": 6.0,
      "From": 3,
      "Message": "확인, 도킹 해제 체크리스트를 따라 도킹 해제를 준비하세요. 완료되면 READY를 누르세요.",
      "Value1": 0.0,
      "Value2": 0.0,
      "Value3": 0.0,
      "String1": "READY",
      "String2": "",
      "String3": "",
      "Bool1": false,
      "ThresholdLimit": 0.0,
      "PinID": 0,
      "PinPosition": 0,
      "KnobID": 0,
      "ButtonId": 0,
      "FuseID": 0,
      "FusePosition": 0,
      "LM_PinID": 0,
      "LM_PinPosition": 0,
      "LM_KnobID": 0,
      "LM_ButtonId": 0,
      "LM_FuseID": 0,
      "LM_FusePosition": 0,
      "Fault": 0,
      "Failure": 0,
      "PlayAudioClip_String3": false
    },
    {
      "Delivered": false,
      "Processed": false,
      "Completed": false,
      "Priority": false,
      "ID": "da34cb40-5042-4af1-8a34-78b2871150d7",
      "Action": 174,
      "Timestamp": 25.0,
      "DisplayTime": 6.0,
      "From": 1,
      "Message": "확인, 도킹 해제를 완료하세요. 여정에 행운을 빕니다, 우주 프로그램에 있어 대단한 업적이 될 것입니다.",
      "Value1": 0.0,
      "Value2": 0.0,
      "Value3": 0.0,
      "String1": "",
      "String2": "",
      "String3": "",
      "Bool1": false,
      "ThresholdLimit": 0.0,
      "PinID": 0,
      "PinPosition": 0,
      "KnobID": 0,
      "ButtonId": 0,
      "FuseID": 0,
      "FusePosition": 0,
      "LM_PinID": 0,
      "LM_PinPosition": 0,
      "LM_KnobID": 0,
      "LM_ButtonId": 0,
      "LM_FuseID": 0,
      "LM_FusePosition": 0,
      "Fault": 0,
      "Failure": 0,
      "PlayAudioClip_String3": false
    },
    {
      "Delivered": false,
      "Processed": false,
      "Completed": false,
      "Priority": false,
      "ID": "550f1f55-42f5-4630-b9f6-b825d3994e1f",
      "Action": 0,
      "Timestamp": 25.0,
      "DisplayTime": 6.0,
      "From": 0,
      "Message": "도킹 해제, 달착륙선에 날개가 생겼습니다. ",
      "Value1": 0.0,
      "Value2": 0.0,
      "Value3": 0.0,
      "String1": "",
      "String2": "",
      "String3": "",
      "Bool1": false,
      "ThresholdLimit": 0.0,
      "PinID": 0,
      "PinPosition": 0,
      "KnobID": 0,
      "ButtonId": 0,
      "FuseID": 0,
      "FusePosition": 0,
      "LM_PinID": 0,
      "LM_PinPosition": 0,
      "LM_KnobID": 0,
      "LM_ButtonId": 0,
      "LM_FuseID": 0,
      "LM_FusePosition": 0,
      "Fault": 0,
      "Failure": 0,
      "PlayAudioClip_String3": false
    },
    {
      "Delivered": false,
      "Processed": false,
      "Completed": false,
      "Priority": false,
      "ID": "160c929d-4e29-4386-9a49-91c34ac487d5",
      "Action": 0,
      "Timestamp": 25.0,
      "DisplayTime": 6.0,
      "From": 3,
      "Message": "좋습니다, 자 갑시다.",
      "Value1": 0.0,
      "Value2": 0.0,
      "Value3": 0.0,
      "String1": "",
      "String2": "",
      "String3": "",
      "Bool1": false,
      "ThresholdLimit": 0.0,
      "PinID": 0,
      "PinPosition": 0,
      "KnobID": 0,
      "ButtonId": 0,
      "FuseID": 0,
      "FusePosition": 0,
      "LM_PinID": 0,
      "LM_PinPosition": 0,
      "LM_KnobID": 0,
      "LM_ButtonId": 0,
      "LM_FuseID": 0,
      "LM_FusePosition": 0,
      "Fault": 0,
      "Failure": 0,
      "PlayAudioClip_String3": false
    },
    {
      "Delivered": false,
      "Processed": false,
      "Completed": false,
      "Priority": false,
      "ID": "01ee1be9-4e27-4734-9182-62c9b0e0e7a8",
      "Action": 1,
      "Timestamp": 25.0,
      "DisplayTime": 6.0,
      "From": 3,
      "Message": "컨트롤을 한번 사용해 LM의 자세를 기동해보고, CSM을 마주보게 한 다음, CSM 창을 통해 다리가 전개되었는지 확인하세요. 다음으로 넘어갈 준비가 되면 READY를 누르세요.",
      "Value1": 0.0,
      "Value2": 0.0,
      "Value3": 0.0,
      "String1": "READY",
      "String2": "",
      "String3": "",
      "Bool1": false,
      "ThresholdLimit": 0.0,
      "PinID": 0,
      "PinPosition": 0,
      "KnobID": 0,
      "ButtonId": 0,
      "FuseID": 0,
      "FusePosition": 0,
      "LM_PinID": 0,
      "LM_PinPosition": 0,
      "LM_KnobID": 0,
      "LM_ButtonId": 0,
      "LM_FuseID": 0,
      "LM_FusePosition": 0,
      "Fault": 0,
      "Failure": 0,
      "PlayAudioClip_String3": false
    },
    {
      "Delivered": false,
      "Processed": false,
      "Completed": false,
      "Priority": false,
      "ID": "8d47b42e-8cb8-4a97-99d3-f273fe038b69",
      "Action": 0,
      "Timestamp": 25.0,
      "DisplayTime": 6.0,
      "From": 0,
      "Message": "좋습니다, 진행합시다.",
      "Value1": 0.0,
      "Value2": 0.0,
      "Value3": 0.0,
      "String1": "",
      "String2": "",
      "String3": "",
      "Bool1": false,
      "ThresholdLimit": 0.0,
      "PinID": 0,
      "PinPosition": 0,
      "KnobID": 0,
      "ButtonId": 0,
      "FuseID": 0,
      "FusePosition": 0,
      "LM_PinID": 0,
      "LM_PinPosition": 0,
      "LM_KnobID": 0,
      "LM_ButtonId": 0,
      "LM_FuseID": 0,
      "LM_FusePosition": 0,
      "Fault": 0,
      "Failure": 0,
      "PlayAudioClip_String3": false
    },
    {
      "Delivered": false,
      "Processed": false,
      "Completed": false,
      "Priority": false,
      "ID": "a8516037-8630-49ab-b01d-bd3c86294056",
      "Action": 1,
      "Timestamp": 25.0,
      "DisplayTime": 6.0,
      "From": 1,
      "Message": "Crew Menu를 사용해 Ap에서 CSM 자동 순환 기동을 계획하세요. Ap 고도를 nmi 단위로(약 59.0이어야 함) 텍스트 상자에 입력한 다음 REQUEST를 누르면 됩니다. 준비되면 알려주세요.",
      "Value1": 0.0,
      "Value2": 0.0,
      "Value3": 0.0,
      "String1": "READY",
      "String2": "",
      "String3": "",
      "Bool1": false,
      "ThresholdLimit": 0.0,
      "PinID": 0,
      "PinPosition": 0,
      "KnobID": 0,
      "ButtonId": 0,
      "FuseID": 0,
      "FusePosition": 0,
      "LM_PinID": 0,
      "LM_PinPosition": 0,
      "LM_KnobID": 0,
      "LM_ButtonId": 0,
      "LM_FuseID": 0,
      "LM_FusePosition": 0,
      "Fault": 0,
      "Failure": 0,
      "PlayAudioClip_String3": false
    },
    {
      "Delivered": false,
      "Processed": false,
      "Completed": false,
      "Priority": false,
      "ID": "75d91b22-6144-474b-98f4-261087373dc1",
      "Action": 4005,
      "Timestamp": 25.0,
      "DisplayTime": 6.0,
      "From": 3,
      "Message": "확인, Pe에 도달하면 점화 지점과 착륙 지점을 통과하게 됩니다. 필요에 따라 타임스케일을 사용하세요.",
      "Value1": 10.0,
      "Value2": 0.0,
      "Value3": 0.0,
      "String1": "",
      "String2": "",
      "String3": "",
      "Bool1": false,
      "ThresholdLimit": 0.0,
      "PinID": 0,
      "PinPosition": 0,
      "KnobID": 0,
      "ButtonId": 0,
      "FuseID": 0,
      "FusePosition": 0,
      "LM_PinID": 0,
      "LM_PinPosition": 0,
      "LM_KnobID": 0,
      "LM_ButtonId": 0,
      "LM_FuseID": 0,
      "LM_FusePosition": 0,
      "Fault": 0,
      "Failure": 0,
      "PlayAudioClip_String3": false
    },
    {
      "Delivered": false,
      "Processed": false,
      "Completed": false,
      "Priority": false,
      "ID": "f45f40e1-583e-464d-ae9a-59f09648f0fd",
      "Action": 0,
      "Timestamp": 25.0,
      "DisplayTime": 6.0,
      "From": 3,
      "Message": "좋습니다, 점화 지점에 가까워지고 있는 것 같습니다. LM의 자세를 비행 경로를 마주보도록 바꾸고, 피치를 내려 우리의 하강 모습, 아래의 지형, 착륙 지점을 시야에 확보하세요.",
      "Value1": 0.0,
      "Value2": 0.0,
      "Value3": 0.0,
      "String1": "",
      "String2": "",
      "String3": "",
      "Bool1": false,
      "ThresholdLimit": 0.0,
      "PinID": 0,
      "PinPosition": 0,
      "KnobID": 0,
      "ButtonId": 0,
      "FuseID": 0,
      "FusePosition": 0,
      "LM_PinID": 0,
      "LM_PinPosition": 0,
      "LM_KnobID": 0,
      "LM_ButtonId": 0,
      "LM_FuseID": 0,
      "LM_FusePosition": 0,
      "Fault": 0,
      "Failure": 0,
      "PlayAudioClip_String3": false
    },
    {
      "Delivered": false,
      "Processed": false,
      "Completed": false,
      "Priority": false,
      "ID": "71765bb7-ba46-45ed-ad0e-0321344c9da2",
      "Action": 0,
      "Timestamp": 25.0,
      "DisplayTime": 120.0,
      "From": 0,
      "Message": "확인, 그렇게 하겠습니다.",
      "Value1": 0.0,
      "Value2": 0.0,
      "Value3": 0.0,
      "String1": "",
      "String2": "",
      "String3": "",
      "Bool1": false,
      "ThresholdLimit": 0.0,
      "PinID": 0,
      "PinPosition": 0,
      "KnobID": 0,
      "ButtonId": 0,
      "FuseID": 0,
      "FusePosition": 0,
      "LM_PinID": 0,
      "LM_PinPosition": 0,
      "LM_KnobID": 0,
      "LM_ButtonId": 0,
      "LM_FuseID": 0,
      "LM_FusePosition": 0,
      "Fault": 0,
      "Failure": 0,
      "PlayAudioClip_String3": false
    },
    {
      "Delivered": false,
      "Processed": false,
      "Completed": false,
      "Priority": false,
      "ID": "348eff29-115d-4193-acf4-23a9d9a961ae",
      "Action": 1004,
      "Timestamp": 25.0,
      "DisplayTime": 6.0,
      "From": 0,
      "Message": "하강을 위한 준비가 된 것 같습니다. 다음 Pe 통과 시, 실제 하강을 수행하겠습니다. 수고하셨습니다, 이것으로 이 미션 단계가 완료됩니다.",
      "Value1": 0.0,
      "Value2": 0.0,
      "Value3": 0.0,
      "String1": "",
      "String2": "",
      "String3": "",
      "Bool1": false,
      "ThresholdLimit": 0.0,
      "PinID": 0,
      "PinPosition": 0,
      "KnobID": 0,
      "ButtonId": 0,
      "FuseID": 0,
      "FusePosition": 0,
      "LM_PinID": 0,
      "LM_PinPosition": 0,
      "LM_KnobID": 0,
      "LM_ButtonId": 0,
      "LM_FuseID": 0,
      "LM_FusePosition": 0,
      "Fault": 0,
      "Failure": 0,
      "PlayAudioClip_String3": false
    }
  ],
  "MissionGoals": [
    {
      "Progress": null,
      "Completed": false,
      "Type": 0,
      "Description": "이 미션 단계를 완료하세요",
      "Target1": 0.0,
      "Target2": 0.0,
      "Target3": 0.0,
      "String1": "",
      "String2": ""
    }
  ],
  "MissionActivities": [],
  "MissionChecklists": [],
  "Comment": "",
  "SpaceProgram": 2,
  "Id": 7854578,
  "ID": "1141fe61-1ad4-42a1-938e-d0db3c481f6d",
  "Title": "DOI와 LEM",
  "Description": "CSM/LM이 달 주위 60 nmi 원형 궤도에 진입했습니다. 이번 미션 단계에서는 CSM/LM을 하강 궤도(Descent Orbit)로 진입시킵니다. 이는 60 nmi x 8 nmi 궤도로, 근지점(Pe)은 예정된 착륙 지점인 고요의 바다(The Sea of Tranquility) 350 nmi 전방에 위치합니다.\n\n달착륙선도 CSM에서 도킹 해제되기 전에 활성화됩니다.",
  "BriefingText": "비행 계획\r\n- 하강 궤도 진입\r\n- 동력 하강 및 달 착륙\r\n- 달 체류\r\n- 상승 및 랑데부\r\n- 지구 전이 궤도 진입\r\n- 진입 및 착륙\n\n1) DOI\n\n2) LM 활성화\n\n3) LM 도킹 해제",
  "FlightPlanPrefabId": 0,
  "MinutesBeforeLaunch": 60.0,
  "TargetAp": 0.0,
  "TargetPe": 0.0,
  "Inclination": 28.91,
  "DeltaRoll": 75.5,
  "CommandModulePilot": "Wood",
  "LunarModulePilot": "Thompson",
  "DisableDefaultAudioSFX": false,
  "LoadState": "StateM4.json",
  "EarthRotationOffsetDegrees": 0.0,
  "Payload": 1,
  "AllowRandomFailures": false,
  "RealisticRadioRange": false,
  "OverrideSunPhase": false,
  "OverrideSunPhaseValue": 180.0,
  "OverridePanelStateCM": false,
  "OverridePanelStateFileNameCM": "Default/Ingress.json",
  "OverridePanelStateLM": false,
  "OverridePanelStateFileNameLM": "Default/Ingress.json",
  "AlwaysSyncMissionCycleTimerWithMET": false
}